{"namespace":"BadaBhaiDesignSystem_01ff85","components":[{"name":"BadaBhaiLogo","sourcePath":"components/brand/BadaBhaiLogo.jsx"},{"name":"ChatBubble","sourcePath":"components/brand/ChatBubble.jsx"},{"name":"JobCard","sourcePath":"components/brand/JobCard.jsx"},{"name":"MaskedCandidate","sourcePath":"components/brand/MaskedCandidate.jsx"},{"name":"Avatar","sourcePath":"components/display/Avatar.jsx"},{"name":"Badge","sourcePath":"components/display/Badge.jsx"},{"name":"Card","sourcePath":"components/display/Card.jsx"},{"name":"Chip","sourcePath":"components/display/Chip.jsx"},{"name":"StatTile","sourcePath":"components/display/StatTile.jsx"},{"name":"Dialog","sourcePath":"components/feedback/Dialog.jsx"},{"name":"ProgressBar","sourcePath":"components/feedback/ProgressBar.jsx"},{"name":"Toast","sourcePath":"components/feedback/Toast.jsx"},{"name":"Tooltip","sourcePath":"components/feedback/Tooltip.jsx"},{"name":"Button","sourcePath":"components/forms/Button.jsx"},{"name":"Checkbox","sourcePath":"components/forms/Checkbox.jsx"},{"name":"IconButton","sourcePath":"components/forms/IconButton.jsx"},{"name":"Input","sourcePath":"components/forms/Input.jsx"},{"name":"OtpInput","sourcePath":"components/forms/OtpInput.jsx"},{"name":"Radio","sourcePath":"components/forms/Radio.jsx"},{"name":"Select","sourcePath":"components/forms/Select.jsx"},{"name":"Switch","sourcePath":"components/forms/Switch.jsx"},{"name":"Textarea","sourcePath":"components/forms/Textarea.jsx"},{"name":"BottomNav","sourcePath":"components/navigation/BottomNav.jsx"},{"name":"Tabs","sourcePath":"components/navigation/Tabs.jsx"}],"startingPoints":[],"cards":[{"path":"guidelines/brand-logo.html","group":"Brand","viewport":"700x250","subtitle":"🟠 Placeholder lockup — Baloo 2 wordmark + chat-lift mark.","name":"Logo & app icon"},{"path":"guidelines/brand-masking.html","group":"Brand","viewport":"700x250","subtitle":"Candidates are masked until unlocked. A first-class pattern.","name":"The masking motif"},{"path":"guidelines/brand-voice.html","group":"Brand","viewport":"700x260","subtitle":"Helpful big brother. Never tests, only helps.","name":"Voice & tone"},{"path":"guidelines/motion.html","group":"Brand","viewport":"700x230","subtitle":"Short ease-out everywhere; one spring for success.","name":"Motion — the stamp"},{"path":"guidelines/color-festive.html","group":"Colors","viewport":"700x180","subtitle":"Saffron, green, rani-pink, turquoise — the Desi Pop palette.","name":"Festive accents"},{"path":"guidelines/color-ink.html","group":"Colors","viewport":"700x172","subtitle":"Warm brown — text, chrome, earthy dark sections.","name":"Ink — warm neutrals"},{"path":"guidelines/color-marigold.html","group":"Colors","viewport":"700x172","subtitle":"Sindoor red — the BadaBhai brand. #E0371C base.","name":"Vermilion — brand"},{"path":"guidelines/color-status.html","group":"Colors","viewport":"700x196","subtitle":"Green (go), crimson (skip), saffron (warn), teal (info).","name":"Status & support"},{"path":"guidelines/color-surfaces.html","group":"Colors","viewport":"700x180","subtitle":"Warm paper page, crisp white cards, ink for dark blocks.","name":"Surfaces — paper & ink"},{"path":"ui_kits/company-web/index.html","group":"Company / Agency Web","viewport":"1280x820","subtitle":"Role-aware demand loop: post → browse masked → unlock → contact","name":"Company / Agency web app"},{"path":"components/brand/brand.card.html","group":"Components","viewport":"700x680","subtitle":"Logo, chat bubbles, swipe job card, masked candidate","name":"Brand primitives"},{"path":"components/display/display.card.html","group":"Components","viewport":"700x540","subtitle":"Card, badge, chip, avatar, stat tile","name":"Display"},{"path":"components/feedback/feedback.card.html","group":"Components","viewport":"700x540","subtitle":"Dialog / sheet, toast, tooltip, progress","name":"Feedback"},{"path":"components/forms/forms.card.html","group":"Components","viewport":"700x620","subtitle":"Buttons, inputs, choices, switch, OTP","name":"Forms"},{"path":"components/navigation/navigation.card.html","group":"Components","viewport":"700x320","subtitle":"Tabs (underline / segmented) + worker bottom nav","name":"Navigation"},{"path":"guidelines/elevation.html","group":"Spacing","viewport":"700x210","subtitle":"Warm, low, ink-tinted. Marigold glow for the one CTA.","name":"Elevation"},{"path":"guidelines/spacing-radii.html","group":"Spacing","viewport":"700x190","subtitle":"Friendly but sturdy. Controls 14, cards 18, pills for chips.","name":"Corner radius"},{"path":"guidelines/spacing-scale.html","group":"Spacing","viewport":"700x250","subtitle":"4px base grid. Tokens --space-1 … --space-13.","name":"Spacing scale"},{"path":"guidelines/spacing-touch.html","group":"Spacing","viewport":"700x190","subtitle":"48px floor in the worker app. Gloved hands, the field.","name":"Touch targets"},{"path":"guidelines/type-body.html","group":"Type","viewport":"700x250","subtitle":"Calm, legible, multilingual. Body never below 16px.","name":"Body & UI — Mukta"},{"path":"guidelines/type-display.html","group":"Type","viewport":"700x230","subtitle":"The voice of bada bhai. Warm, rounded, encouraging.","name":"Display — Baloo 2"},{"path":"guidelines/type-mono.html","group":"Type","viewport":"700x210","subtitle":"Self-hosted. Money, IDs, counts. Tabular numerals.","name":"Data — Roboto Mono"},{"path":"guidelines/type-multilingual.html","group":"Type","viewport":"700x250","subtitle":"Devanagari + Latin in one voice. Both families carry it.","name":"Hinglish & multilingual"},{"path":"guidelines/type-scale.html","group":"Type","viewport":"700x300","subtitle":"Mobile-first ramp, 11 → 76px. Body floor 16px.","name":"Type scale"},{"path":"android-build-kit/index.html","group":"Worker App","viewport":"440x920","subtitle":"17 screens, end to end · Desi Vernacular Pop","name":"Worker App — full flow (Android kit)"},{"path":"ui_kits/worker-app/index.html","group":"Worker App","viewport":"430x900","subtitle":"Login → chat onboarding → resume → swipe-to-apply feed","name":"Worker mobile app"}],"templates":[{"name":"Company Dashboard","description":"Payer KPIs + masked candidate list ready to unlock","folder":"templates/company-dashboard","entryPath":"templates/company-dashboard/CompanyDashboard.dc.html","thumbnail":{"path":"templates/company-dashboard/.thumbnail","kind":"captured"}},{"name":"Worker Job Feed","description":"Mobile worker screen: filter chips + swipe-to-apply job card","folder":"templates/worker-screen","entryPath":"templates/worker-screen/WorkerJobFeed.dc.html","thumbnail":{"path":"templates/worker-screen/.thumbnail","kind":"captured"}}],"hasThumbnailHtml":false,"globalCssPaths":["tokens/fonts.css","tokens/colors.css","tokens/typography.css","tokens/spacing.css","tokens/radii.css","tokens/elevation.css","tokens/motion.css","tokens/base.css","components/forms/forms.css","components/display/display.css","components/feedback/feedback.css","components/navigation/navigation.css","components/brand/brand.css","components.css","styles.css"],"tokens":[{"name":"--vermilion-50","value":"#FCEAE3","kind":"color","definedIn":"tokens/colors.css"},{"name":"--vermilion-100","value":"#F8D0C3","kind":"color","definedIn":"tokens/colors.css"},{"name":"--vermilion-200","value":"#F1A78F","kind":"color","definedIn":"tokens/colors.css"},{"name":"--vermilion-300","value":"#E97D5E","kind":"color","definedIn":"tokens/colors.css"},{"name":"--vermilion-400","value":"#E35636","kind":"color","definedIn":"tokens/colors.css"},{"name":"--vermilion-500","value":"#E0371C","kind":"color","definedIn":"tokens/colors.css"},{"name":"--vermilion-600","value":"#C22A12","kind":"color","definedIn":"tokens/colors.css"},{"name":"--vermilion-700","value":"#9C220F","kind":"color","definedIn":"tokens/colors.css"},{"name":"--vermilion-800","value":"#7B1D11","kind":"color","definedIn":"tokens/colors.css"},{"name":"--vermilion-900","value":"#641A10","kind":"color","definedIn":"tokens/colors.css"},{"name":"--saffron-50","value":"#FEF4DD","kind":"color","definedIn":"tokens/colors.css"},{"name":"--saffron-100","value":"#FBE3AC","kind":"color","definedIn":"tokens/colors.css"},{"name":"--saffron-200","value":"#F8CD6B","kind":"color","definedIn":"tokens/colors.css"},{"name":"--saffron-300","value":"#F5B435","kind":"color","definedIn":"tokens/colors.css"},{"name":"--saffron-400","value":"#F29D10","kind":"color","definedIn":"tokens/colors.css"},{"name":"--saffron-500","value":"#E5870A","kind":"color","definedIn":"tokens/colors.css"},{"name":"--saffron-600","value":"#C06E08","kind":"color","definedIn":"tokens/colors.css"},{"name":"--saffron-700","value":"#965507","kind":"color","definedIn":"tokens/colors.css"},{"name":"--green-50","value":"#E5F4ED","kind":"color","definedIn":"tokens/colors.css"},{"name":"--green-100","value":"#C2E6D3","kind":"color","definedIn":"tokens/colors.css"},{"name":"--green-200","value":"#8FD0AE","kind":"color","definedIn":"tokens/colors.css"},{"name":"--green-300","value":"#52B384","kind":"color","definedIn":"tokens/colors.css"},{"name":"--green-500","value":"#0E7A4F","kind":"color","definedIn":"tokens/colors.css"},{"name":"--green-600","value":"#0A6341","kind":"color","definedIn":"tokens/colors.css"},{"name":"--green-700","value":"#084D33","kind":"color","definedIn":"tokens/colors.css"},{"name":"--pink-50","value":"#FBE7F0","kind":"color","definedIn":"tokens/colors.css"},{"name":"--pink-100","value":"#F4C2D9","kind":"color","definedIn":"tokens/colors.css"},{"name":"--pink-500","value":"#C2186A","kind":"color","definedIn":"tokens/colors.css"},{"name":"--pink-600","value":"#A01357","kind":"color","definedIn":"tokens/colors.css"},{"name":"--teal-50","value":"#E2F3F3","kind":"color","definedIn":"tokens/colors.css"},{"name":"--teal-100","value":"#BEE5E5","kind":"color","definedIn":"tokens/colors.css"},{"name":"--teal-500","value":"#0E8488","kind":"color","definedIn":"tokens/colors.css"},{"name":"--teal-600","value":"#0A6A6E","kind":"color","definedIn":"tokens/colors.css"},{"name":"--teal-700","value":"#08565A","kind":"color","definedIn":"tokens/colors.css"},{"name":"--red-50","value":"#FCE9EB","kind":"color","definedIn":"tokens/colors.css"},{"name":"--red-100","value":"#F7CBD0","kind":"color","definedIn":"tokens/colors.css"},{"name":"--red-300","value":"#E5808B","kind":"color","definedIn":"tokens/colors.css"},{"name":"--red-500","value":"#C8142C","kind":"color","definedIn":"tokens/colors.css"},{"name":"--red-600","value":"#A50F23","kind":"color","definedIn":"tokens/colors.css"},{"name":"--red-700","value":"#820B1B","kind":"color","definedIn":"tokens/colors.css"},{"name":"--ink-950","value":"#1C1108","kind":"color","definedIn":"tokens/colors.css"},{"name":"--ink-900","value":"#2A1A0E","kind":"color","definedIn":"tokens/colors.css"},{"name":"--ink-800","value":"#3D2A1A","kind":"color","definedIn":"tokens/colors.css"},{"name":"--ink-700","value":"#523A26","kind":"color","definedIn":"tokens/colors.css"},{"name":"--ink-600","value":"#6E5238","kind":"color","definedIn":"tokens/colors.css"},{"name":"--ink-500","value":"#8E7252","kind":"color","definedIn":"tokens/colors.css"},{"name":"--ink-400","value":"#B29977","kind":"color","definedIn":"tokens/colors.css"},{"name":"--ink-300","value":"#D3BF9F","kind":"color","definedIn":"tokens/colors.css"},{"name":"--ink-200","value":"#E7D9C2","kind":"color","definedIn":"tokens/colors.css"},{"name":"--ink-100","value":"#F1E7D5","kind":"color","definedIn":"tokens/colors.css"},{"name":"--ink-50","value":"#F8F1E4","kind":"color","definedIn":"tokens/colors.css"},{"name":"--paper-0","value":"#FFFFFF","kind":"color","definedIn":"tokens/colors.css"},{"name":"--paper-1","value":"#FFFDF8","kind":"color","definedIn":"tokens/colors.css"},{"name":"--paper-2","value":"#FFF6E8","kind":"color","definedIn":"tokens/colors.css"},{"name":"--paper-3","value":"#FBEAD0","kind":"color","definedIn":"tokens/colors.css"},{"name":"--paper-4","value":"#F4DEBE","kind":"color","definedIn":"tokens/colors.css"},{"name":"--marigold-50","value":"var(--vermilion-50)","kind":"color","definedIn":"tokens/colors.css"},{"name":"--marigold-100","value":"var(--vermilion-100)","kind":"color","definedIn":"tokens/colors.css"},{"name":"--marigold-200","value":"var(--vermilion-200)","kind":"color","definedIn":"tokens/colors.css"},{"name":"--marigold-300","value":"var(--vermilion-300)","kind":"color","definedIn":"tokens/colors.css"},{"name":"--marigold-400","value":"var(--vermilion-400)","kind":"color","definedIn":"tokens/colors.css"},{"name":"--marigold-500","value":"var(--vermilion-500)","kind":"color","definedIn":"tokens/colors.css"},{"name":"--marigold-600","value":"var(--vermilion-600)","kind":"color","definedIn":"tokens/colors.css"},{"name":"--marigold-700","value":"var(--vermilion-700)","kind":"color","definedIn":"tokens/colors.css"},{"name":"--marigold-800","value":"var(--vermilion-800)","kind":"color","definedIn":"tokens/colors.css"},{"name":"--marigold-900","value":"var(--vermilion-900)","kind":"color","definedIn":"tokens/colors.css"},{"name":"--text-primary","value":"var(--ink-900)","kind":"font","definedIn":"tokens/colors.css"},{"name":"--text-secondary","value":"var(--ink-600)","kind":"font","definedIn":"tokens/colors.css"},{"name":"--text-muted","value":"var(--ink-500)","kind":"font","definedIn":"tokens/colors.css"},{"name":"--text-faint","value":"var(--ink-400)","kind":"font","definedIn":"tokens/colors.css"},{"name":"--text-inverse","value":"var(--paper-1)","kind":"font","definedIn":"tokens/colors.css"},{"name":"--text-brand","value":"var(--vermilion-700)","kind":"font","definedIn":"tokens/colors.css"},{"name":"--text-on-brand","value":"#FFFFFF","kind":"font","definedIn":"tokens/colors.css"},{"name":"--text-link","value":"var(--green-600)","kind":"font","definedIn":"tokens/colors.css"},{"name":"--surface-page","value":"var(--paper-2)","kind":"color","definedIn":"tokens/colors.css"},{"name":"--surface-card","value":"var(--paper-0)","kind":"color","definedIn":"tokens/colors.css"},{"name":"--surface-raised","value":"var(--paper-1)","kind":"color","definedIn":"tokens/colors.css"},{"name":"--surface-sunken","value":"var(--paper-3)","kind":"color","definedIn":"tokens/colors.css"},{"name":"--surface-inset","value":"var(--paper-4)","kind":"color","definedIn":"tokens/colors.css"},{"name":"--surface-ink","value":"var(--ink-900)","kind":"color","definedIn":"tokens/colors.css"},{"name":"--surface-ink-2","value":"var(--ink-800)","kind":"color","definedIn":"tokens/colors.css"},{"name":"--brand","value":"var(--vermilion-500)","kind":"color","definedIn":"tokens/colors.css"},{"name":"--brand-hover","value":"var(--vermilion-600)","kind":"color","definedIn":"tokens/colors.css"},{"name":"--brand-press","value":"var(--vermilion-700)","kind":"color","definedIn":"tokens/colors.css"},{"name":"--brand-tint","value":"var(--vermilion-50)","kind":"color","definedIn":"tokens/colors.css"},{"name":"--brand-tint-2","value":"var(--vermilion-100)","kind":"color","definedIn":"tokens/colors.css"},{"name":"--brand-border","value":"var(--vermilion-200)","kind":"color","definedIn":"tokens/colors.css"},{"name":"--saffron","value":"var(--saffron-400)","kind":"color","definedIn":"tokens/colors.css"},{"name":"--saffron-deep","value":"var(--saffron-600)","kind":"color","definedIn":"tokens/colors.css"},{"name":"--pink","value":"var(--pink-500)","kind":"color","definedIn":"tokens/colors.css"},{"name":"--teal","value":"var(--teal-500)","kind":"color","definedIn":"tokens/colors.css"},{"name":"--success","value":"var(--green-500)","kind":"color","definedIn":"tokens/colors.css"},{"name":"--success-press","value":"var(--green-600)","kind":"color","definedIn":"tokens/colors.css"},{"name":"--success-tint","value":"var(--green-50)","kind":"color","definedIn":"tokens/colors.css"},{"name":"--danger","value":"var(--red-500)","kind":"color","definedIn":"tokens/colors.css"},{"name":"--danger-press","value":"var(--red-600)","kind":"color","definedIn":"tokens/colors.css"},{"name":"--danger-tint","value":"var(--red-50)","kind":"color","definedIn":"tokens/colors.css"},{"name":"--warning","value":"var(--saffron-600)","kind":"color","definedIn":"tokens/colors.css"},{"name":"--warning-tint","value":"var(--saffron-50)","kind":"color","definedIn":"tokens/colors.css"},{"name":"--info","value":"var(--teal-500)","kind":"color","definedIn":"tokens/colors.css"},{"name":"--info-tint","value":"var(--teal-50)","kind":"color","definedIn":"tokens/colors.css"},{"name":"--border-subtle","value":"rgba(42, 26, 14, 0.10)","kind":"color","definedIn":"tokens/colors.css"},{"name":"--border-default","value":"rgba(42, 26, 14, 0.15)","kind":"color","definedIn":"tokens/colors.css"},{"name":"--border-strong","value":"rgba(42, 26, 14, 0.26)","kind":"color","definedIn":"tokens/colors.css"},{"name":"--border-ink","value":"var(--ink-800)","kind":"color","definedIn":"tokens/colors.css"},{"name":"--divider","value":"rgba(42, 26, 14, 0.09)","kind":"color","definedIn":"tokens/colors.css"},{"name":"--border-festive","value":"2px dashed var(--green-500)","kind":"color","definedIn":"tokens/colors.css"},{"name":"--border-double","value":"3px double var(--vermilion-500)","kind":"color","definedIn":"tokens/colors.css"},{"name":"--ring","value":"rgba(224, 55, 28, 0.42)","kind":"color","definedIn":"tokens/colors.css"},{"name":"--scrim","value":"rgba(28, 17, 8, 0.56)","kind":"color","definedIn":"tokens/colors.css"},{"name":"--text-primary","value":"var(--paper-1)","kind":"font","definedIn":"tokens/colors.css","scope":"[data-theme=\"ink\"]"},{"name":"--text-secondary","value":"var(--ink-200)","kind":"font","definedIn":"tokens/colors.css","scope":"[data-theme=\"ink\"]"},{"name":"--text-muted","value":"var(--ink-300)","kind":"font","definedIn":"tokens/colors.css","scope":"[data-theme=\"ink\"]"},{"name":"--text-faint","value":"var(--ink-400)","kind":"font","definedIn":"tokens/colors.css","scope":"[data-theme=\"ink\"]"},{"name":"--text-inverse","value":"var(--ink-900)","kind":"font","definedIn":"tokens/colors.css","scope":"[data-theme=\"ink\"]"},{"name":"--text-brand","value":"var(--vermilion-300)","kind":"font","definedIn":"tokens/colors.css","scope":"[data-theme=\"ink\"]"},{"name":"--text-link","value":"var(--green-300)","kind":"font","definedIn":"tokens/colors.css","scope":"[data-theme=\"ink\"]"},{"name":"--surface-page","value":"var(--ink-950)","kind":"color","definedIn":"tokens/colors.css","scope":"[data-theme=\"ink\"]"},{"name":"--surface-card","value":"var(--ink-900)","kind":"color","definedIn":"tokens/colors.css","scope":"[data-theme=\"ink\"]"},{"name":"--surface-raised","value":"var(--ink-800)","kind":"color","definedIn":"tokens/colors.css","scope":"[data-theme=\"ink\"]"},{"name":"--surface-sunken","value":"#150C06","kind":"color","definedIn":"tokens/colors.css","scope":"[data-theme=\"ink\"]"},{"name":"--surface-inset","value":"#100A05","kind":"color","definedIn":"tokens/colors.css","scope":"[data-theme=\"ink\"]"},{"name":"--brand-tint","value":"rgba(224, 55, 28, 0.18)","kind":"color","definedIn":"tokens/colors.css","scope":"[data-theme=\"ink\"]"},{"name":"--brand-tint-2","value":"rgba(224, 55, 28, 0.26)","kind":"color","definedIn":"tokens/colors.css","scope":"[data-theme=\"ink\"]"},{"name":"--brand-border","value":"rgba(224, 55, 28, 0.42)","kind":"color","definedIn":"tokens/colors.css","scope":"[data-theme=\"ink\"]"},{"name":"--success-tint","value":"rgba(14, 122, 79, 0.20)","kind":"color","definedIn":"tokens/colors.css","scope":"[data-theme=\"ink\"]"},{"name":"--danger-tint","value":"rgba(200, 20, 44, 0.20)","kind":"color","definedIn":"tokens/colors.css","scope":"[data-theme=\"ink\"]"},{"name":"--warning-tint","value":"rgba(242, 157, 16, 0.18)","kind":"color","definedIn":"tokens/colors.css","scope":"[data-theme=\"ink\"]"},{"name":"--border-subtle","value":"rgba(255, 250, 240, 0.08)","kind":"color","definedIn":"tokens/colors.css","scope":"[data-theme=\"ink\"]"},{"name":"--border-default","value":"rgba(255, 250, 240, 0.15)","kind":"color","definedIn":"tokens/colors.css","scope":"[data-theme=\"ink\"]"},{"name":"--border-strong","value":"rgba(255, 250, 240, 0.26)","kind":"color","definedIn":"tokens/colors.css","scope":"[data-theme=\"ink\"]"},{"name":"--divider","value":"rgba(255, 250, 240, 0.10)","kind":"color","definedIn":"tokens/colors.css","scope":"[data-theme=\"ink\"]"},{"name":"--scrim","value":"rgba(8, 5, 2, 0.66)","kind":"color","definedIn":"tokens/colors.css","scope":"[data-theme=\"ink\"]"},{"name":"--font-display","value":"'Baloo 2', system-ui, -apple-system, 'Segoe UI', sans-serif","kind":"font","definedIn":"tokens/typography.css"},{"name":"--font-sans","value":"'Mukta', system-ui, -apple-system, 'Segoe UI', Roboto, sans-serif","kind":"font","definedIn":"tokens/typography.css"},{"name":"--font-mono","value":"'Roboto Mono', ui-monospace, 'SF Mono', Menlo, monospace","kind":"font","definedIn":"tokens/typography.css"},{"name":"--text-2xs","value":"11px","kind":"font","definedIn":"tokens/typography.css"},{"name":"--text-xs","value":"12px","kind":"font","definedIn":"tokens/typography.css"},{"name":"--text-sm","value":"14px","kind":"font","definedIn":"tokens/typography.css"},{"name":"--text-base","value":"16px","kind":"font","definedIn":"tokens/typography.css"},{"name":"--text-md","value":"18px","kind":"font","definedIn":"tokens/typography.css"},{"name":"--text-lg","value":"20px","kind":"font","definedIn":"tokens/typography.css"},{"name":"--text-xl","value":"24px","kind":"font","definedIn":"tokens/typography.css"},{"name":"--text-2xl","value":"30px","kind":"font","definedIn":"tokens/typography.css"},{"name":"--text-3xl","value":"38px","kind":"font","definedIn":"tokens/typography.css"},{"name":"--text-4xl","value":"48px","kind":"font","definedIn":"tokens/typography.css"},{"name":"--text-5xl","value":"60px","kind":"font","definedIn":"tokens/typography.css"},{"name":"--text-6xl","value":"76px","kind":"font","definedIn":"tokens/typography.css"},{"name":"--weight-light","value":"300","kind":"font","definedIn":"tokens/typography.css"},{"name":"--weight-regular","value":"400","kind":"font","definedIn":"tokens/typography.css"},{"name":"--weight-medium","value":"500","kind":"font","definedIn":"tokens/typography.css"},{"name":"--weight-semibold","value":"600","kind":"font","definedIn":"tokens/typography.css"},{"name":"--weight-bold","value":"700","kind":"font","definedIn":"tokens/typography.css"},{"name":"--weight-extrabold","value":"800","kind":"font","definedIn":"tokens/typography.css"},{"name":"--leading-none","value":"1","kind":"font","definedIn":"tokens/typography.css"},{"name":"--leading-tight","value":"1.1","kind":"font","definedIn":"tokens/typography.css"},{"name":"--leading-snug","value":"1.25","kind":"font","definedIn":"tokens/typography.css"},{"name":"--leading-normal","value":"1.5","kind":"font","definedIn":"tokens/typography.css"},{"name":"--leading-relaxed","value":"1.65","kind":"font","definedIn":"tokens/typography.css"},{"name":"--tracking-tighter","value":"-0.03em","kind":"font","definedIn":"tokens/typography.css"},{"name":"--tracking-tight","value":"-0.015em","kind":"font","definedIn":"tokens/typography.css"},{"name":"--tracking-normal","value":"0","kind":"font","definedIn":"tokens/typography.css"},{"name":"--tracking-wide","value":"0.04em","kind":"font","definedIn":"tokens/typography.css"},{"name":"--tracking-wider","value":"0.09em","kind":"font","definedIn":"tokens/typography.css"},{"name":"--font-eyebrow-size","value":"var(--text-xs)","kind":"font","definedIn":"tokens/typography.css"},{"name":"--font-eyebrow-spacing","value":"var(--tracking-wider)","kind":"font","definedIn":"tokens/typography.css"},{"name":"--font-eyebrow-weight","value":"var(--weight-bold)","kind":"font","definedIn":"tokens/typography.css"},{"name":"--font-body-size","value":"var(--text-base)","kind":"font","definedIn":"tokens/typography.css"},{"name":"--font-body-leading","value":"var(--leading-normal)","kind":"font","definedIn":"tokens/typography.css"},{"name":"--font-display-leading","value":"var(--leading-tight)","kind":"font","definedIn":"tokens/typography.css"},{"name":"--font-display-tracking","value":"var(--tracking-tight)","kind":"font","definedIn":"tokens/typography.css"},{"name":"--space-0","value":"0","kind":"spacing","definedIn":"tokens/spacing.css"},{"name":"--space-1","value":"4px","kind":"spacing","definedIn":"tokens/spacing.css"},{"name":"--space-2","value":"8px","kind":"spacing","definedIn":"tokens/spacing.css"},{"name":"--space-3","value":"12px","kind":"spacing","definedIn":"tokens/spacing.css"},{"name":"--space-4","value":"16px","kind":"spacing","definedIn":"tokens/spacing.css"},{"name":"--space-5","value":"20px","kind":"spacing","definedIn":"tokens/spacing.css"},{"name":"--space-6","value":"24px","kind":"spacing","definedIn":"tokens/spacing.css"},{"name":"--space-7","value":"32px","kind":"spacing","definedIn":"tokens/spacing.css"},{"name":"--space-8","value":"40px","kind":"spacing","definedIn":"tokens/spacing.css"},{"name":"--space-9","value":"48px","kind":"spacing","definedIn":"tokens/spacing.css"},{"name":"--space-10","value":"64px","kind":"spacing","definedIn":"tokens/spacing.css"},{"name":"--space-11","value":"80px","kind":"spacing","definedIn":"tokens/spacing.css"},{"name":"--space-12","value":"96px","kind":"spacing","definedIn":"tokens/spacing.css"},{"name":"--space-13","value":"128px","kind":"spacing","definedIn":"tokens/spacing.css"},{"name":"--space-14","value":"160px","kind":"spacing","definedIn":"tokens/spacing.css"},{"name":"--tap","value":"48px","kind":"spacing","definedIn":"tokens/spacing.css"},{"name":"--control-sm","value":"36px","kind":"spacing","definedIn":"tokens/spacing.css"},{"name":"--control-md","value":"44px","kind":"spacing","definedIn":"tokens/spacing.css"},{"name":"--control-lg","value":"52px","kind":"spacing","definedIn":"tokens/spacing.css"},{"name":"--gutter","value":"20px","kind":"spacing","definedIn":"tokens/spacing.css"},{"name":"--gutter-web","value":"32px","kind":"spacing","definedIn":"tokens/spacing.css"},{"name":"--content-max","value":"1200px","kind":"spacing","definedIn":"tokens/spacing.css"},{"name":"--reading-max","value":"68ch","kind":"spacing","definedIn":"tokens/spacing.css"},{"name":"--app-max","value":"440px","kind":"spacing","definedIn":"tokens/spacing.css"},{"name":"--radius-xs","value":"6px","kind":"radius","definedIn":"tokens/radii.css"},{"name":"--radius-sm","value":"10px","kind":"radius","definedIn":"tokens/radii.css"},{"name":"--radius-md","value":"14px","kind":"radius","definedIn":"tokens/radii.css"},{"name":"--radius-lg","value":"18px","kind":"radius","definedIn":"tokens/radii.css"},{"name":"--radius-xl","value":"24px","kind":"radius","definedIn":"tokens/radii.css"},{"name":"--radius-2xl","value":"32px","kind":"radius","definedIn":"tokens/radii.css"},{"name":"--radius-pill","value":"999px","kind":"radius","definedIn":"tokens/radii.css"},{"name":"--radius-round","value":"50%","kind":"radius","definedIn":"tokens/radii.css"},{"name":"--shadow-xs","value":"0 1px 2px rgba(33, 30, 22, 0.06)","kind":"shadow","definedIn":"tokens/elevation.css"},{"name":"--shadow-sm","value":"0 1px 2px rgba(33, 30, 22, 0.06),\n               0 2px 6px rgba(33, 30, 22, 0.05)","kind":"shadow","definedIn":"tokens/elevation.css"},{"name":"--shadow-md","value":"0 2px 4px rgba(33, 30, 22, 0.05),\n               0 8px 20px rgba(33, 30, 22, 0.09)","kind":"shadow","definedIn":"tokens/elevation.css"},{"name":"--shadow-lg","value":"0 4px 10px rgba(33, 30, 22, 0.06),\n               0 18px 40px rgba(33, 30, 22, 0.14)","kind":"shadow","definedIn":"tokens/elevation.css"},{"name":"--shadow-xl","value":"0 24px 60px rgba(33, 30, 22, 0.22)","kind":"shadow","definedIn":"tokens/elevation.css"},{"name":"--shadow-brand","value":"0 6px 18px rgba(224, 55, 28, 0.34)","kind":"shadow","definedIn":"tokens/elevation.css"},{"name":"--shadow-brand-lg","value":"0 12px 30px rgba(224, 55, 28, 0.40)","kind":"shadow","definedIn":"tokens/elevation.css"},{"name":"--shadow-inset","value":"inset 0 1px 2px rgba(33, 30, 22, 0.10)","kind":"shadow","definedIn":"tokens/elevation.css"},{"name":"--ring-focus","value":"0 0 0 3px var(--ring)","kind":"color","definedIn":"tokens/elevation.css"},{"name":"--ring-focus-tight","value":"0 0 0 2px var(--surface-card), 0 0 0 4px var(--ring)","kind":"color","definedIn":"tokens/elevation.css"},{"name":"--border-hairline","value":"1px","kind":"spacing","definedIn":"tokens/elevation.css"},{"name":"--border-medium","value":"1.5px","kind":"spacing","definedIn":"tokens/elevation.css"},{"name":"--border-bold","value":"2px","kind":"spacing","definedIn":"tokens/elevation.css"},{"name":"--ease-out","value":"cubic-bezier(0.22, 0.61, 0.36, 1)","kind":"other","definedIn":"tokens/motion.css","annotation":"other"},{"name":"--ease-in-out","value":"cubic-bezier(0.62, 0, 0.30, 1)","kind":"other","definedIn":"tokens/motion.css","annotation":"other"},{"name":"--ease-stamp","value":"cubic-bezier(0.18, 0.9, 0.32, 1.28)","kind":"other","definedIn":"tokens/motion.css","annotation":"other"},{"name":"--ease-in","value":"cubic-bezier(0.55, 0, 1, 0.45)","kind":"other","definedIn":"tokens/motion.css","annotation":"other"},{"name":"--duration-instant","value":"0ms","kind":"other","definedIn":"tokens/motion.css","annotation":"other"},{"name":"--duration-fast","value":"0ms","kind":"other","definedIn":"tokens/motion.css","annotation":"other"},{"name":"--duration-base","value":"0ms","kind":"other","definedIn":"tokens/motion.css","annotation":"other"},{"name":"--duration-slow","value":"0ms","kind":"other","definedIn":"tokens/motion.css","annotation":"other"},{"name":"--duration-slower","value":"0ms","kind":"other","definedIn":"tokens/motion.css","annotation":"other"},{"name":"--transition-control","value":"background-color var(--duration-fast) var(--ease-out),\n                        border-color var(--duration-fast) var(--ease-out),\n                        color var(--duration-fast) var(--ease-out),\n                        box-shadow var(--duration-fast) var(--ease-out),\n                        transform var(--duration-fast) var(--ease-out)","kind":"color","definedIn":"tokens/motion.css"},{"name":"--z-base","value":"0","kind":"other","definedIn":"tokens/base.css","annotation":"other"},{"name":"--z-raised","value":"10","kind":"other","definedIn":"tokens/base.css","annotation":"other"},{"name":"--z-sticky","value":"100","kind":"other","definedIn":"tokens/base.css","annotation":"other"},{"name":"--z-nav","value":"200","kind":"other","definedIn":"tokens/base.css","annotation":"other"},{"name":"--z-overlay","value":"1000","kind":"other","definedIn":"tokens/base.css","annotation":"other"},{"name":"--z-modal","value":"1100","kind":"other","definedIn":"tokens/base.css","annotation":"other"},{"name":"--z-toast","value":"1200","kind":"other","definedIn":"tokens/base.css","annotation":"other"},{"name":"--z-tooltip","value":"1300","kind":"other","definedIn":"tokens/base.css","annotation":"other"}],"themes":[{"selector":"[data-theme=\"ink\"]","label":"Ink"}],"fonts":[{"family":"Roboto Mono","weight":"400","style":"normal","cssPath":"tokens/fonts.css","files":["assets/fonts/RobotoMono-Regular.ttf"]},{"family":"Roboto Mono","weight":"700","style":"normal","cssPath":"tokens/fonts.css","files":["assets/fonts/RobotoMono-Bold.ttf"]},{"family":"Roboto Mono","weight":"400","style":"italic","cssPath":"tokens/fonts.css","files":["assets/fonts/RobotoMono-Italic.ttf"]},{"family":"Roboto Mono","weight":"700","style":"italic","cssPath":"tokens/fonts.css","files":["assets/fonts/RobotoMono-BoldItalic.ttf"]}],"brandFonts":[{"family":"Roboto Mono","status":"ok","tokens":["--font-mono"],"path":"tokens/fonts.css"},{"family":"Baloo 2","status":"ok","tokens":["--font-display"],"path":"tokens/typography.css"},{"family":"Mukta","status":"ok","tokens":["--font-sans"],"path":"tokens/typography.css"}],"source":"spa"}